ssd1306_infobutton/PressStart2P-Regular.ttf
ssd1306_infobutton/__init__.py
ssd1306_infobutton-0.1.5.dist-info/LICENSE
ssd1306_infobutton-0.1.5.dist-info/WHEEL
ssd1306_infobutton-0.1.5.dist-info/METADATA
ssd1306_infobutton-0.1.5.dist-info/RECORD
